rsw/Makefile.jinja2
rsw/__init__.py
reSW-0.1.2.dist-info/METADATA
reSW-0.1.2.dist-info/WHEEL
reSW-0.1.2.dist-info/entry_points.txt
reSW-0.1.2.dist-info/top_level.txt
reSW-0.1.2.dist-info/zip-safe
reSW-0.1.2.dist-info/RECORD
