Metadata-Version: 2.1
Name: reSW
Version: 0.1.2
Summary: Highly customizable static site generator for reStructuredText markup
License: GNU General Public License v3 or later (GPLv3+)
Keywords: reStructuredText,SSG,static site generator
Classifier: Programming Language :: Python :: 3.10
Classifier: Operating System :: OS Independent
Requires-Python: >=3.7
Requires-Dist: colorlog (==6.7.0)
Requires-Dist: docopt (==0.6.2)
Requires-Dist: docutils (==0.17.1)
Requires-Dist: Jinja2 (==3.1.2)
Requires-Dist: Pygments (==2.13.0)
Requires-Dist: toml (==0.10.2)
